{
  "name": "praekeltfoundation-seed_stack",
  "version": "0.9.3-dev",
  "author": "Jamie Hewland",
  "summary": "Meta-module for deploying the Seed Stack",
  "license": "BSD-3-Clause",
  "source": "http://github.com/praekeltfoundation/puppet-seed_stack",
  "project_page": "https://github.com/praekeltfoundation/puppet-seed_stack",
  "issues_url": "https://github.com/praekeltfoundation/puppet-seed_stack/issues",
  "dependencies": [
    {
      "name": "praekeltfoundation-consular",
      "version_requirement": ">=0.2.0"
    },
    {
      "name": "praekeltfoundation-gluster",
      "version_requirement": ">=0.2.2 <0.3.0"
    },
    {
      "name": "praekeltfoundation-xylem",
      "version_requirement": ">=0.2.0 <0.3.0"
    },
    {
      "name": "praekeltfoundation-marathon",
      "version_requirement": ">=0.4.0 <0.5.0"
    },
    {
      "name": "praekeltfoundation-webupd8_oracle_java",
      "version_requirement": ">=0.1.2"
    },
    {
      "name": "deric-mesos",
      "version_requirement": ">=0.8.0 <0.9.0"
    },
    {
      "name": "deric-zookeeper",
      "version_requirement": ">=0.5.1 <0.6.0"
    },
    {
      "name": "garethr-docker",
      "version_requirement": ">=4.1.0"
    },
    {
      "name": "gdhbashton-consul_template",
      "version_requirement": ">=0.2.4"
    },
    {
      "name": "KyleAnderson-consul",
      "version_requirement": ">=1.0.4"
    }
  ],
  "requirements": [
    {
      "name": "puppet",
      "version_requirement": ">=3.4.0"
    }
  ],
  "operatingsystem_support": [
    {
      "operatingsystem": "Ubuntu",
      "operatingsystemrelease": [
        "14.04"
      ]
    }
  ]
}
